deep3d/__init__.py
deep3d/test.py
deep3d-0.0.1.dist-info/METADATA
deep3d-0.0.1.dist-info/WHEEL
deep3d-0.0.1.dist-info/top_level.txt
deep3d-0.0.1.dist-info/RECORD
